{
  "CountryId": "1",
  "QuestionNumber": 3,
  "NoEnergyImpact": -5,
  "NoResponseText": "Oh no, now you have to pay double the price when your travel partner decides to take this tour later during your adventure. Your wealth decreases by 10 and your energy descreases by 5.",
  "NoWealthImpact": -10,
  "Tip": "A private pasta-making lesson at a working Tuscan farm? That sounds like fun adventurer.",
  "YesEnergyImpact": 10,
  "YesResponseText": "You've made a great choice adventurer. You Wealth increases by 10 and your energy increases by 10.",
  "YesWealthImpact": 10
}
